{
  "abstract": "Societal or population-level attitudes are aggregated patterns of different individual attitudes, representing collective general predispositions. As service robots become ubiquitous, understanding attitudes towards them at the population (vs. individual) level enables firms to expand robot services to a broad (vs. niche) market. Targeting population-level attitudes would benefit service firms because: (1) they are more persistent, thus, stronger predictors of behavioral patterns and (2) this approach is less reliant on personal data, whereas individualized services are vulnerable to AI-related privacy risks. As for service theory, ignoring broad unobserved differences in attitudes produces biased conclusions, and our systematic review of previous research highlights a poor understanding of potential heterogeneity in attitudes toward service robots. We present five diverse studies (S1–S5), utilizing multinational and “real world” data (N\n                    total\n                    = 89,541; years: 2012–2024). Results reveal a stable structure comprising four distinct attitude profiles (S1–S5):\n                    positive\n                    (“adore”),\n                    negative\n                    (“abhor”),\n                    indifferent\n                    (“ignore”), and\n                    ambivalent\n                    (“unsure”). The psychological need for interacting with service staff, and for autonomy and relatedness in technology use, function as attitude profile antecedents (S2). Importantly, the attitude profiles predict differences in post-interaction discomfort and anxiety (S3), satisfaction ratings and service evaluations (S4), and perceived sociability and uncanniness based on a robot’s humanlikeness (S5).",
  "ai_type_tags": [
    "AI采用",
    "服务机器人"
  ],
  "arxiv_id": null,
  "authors": [
    "Vignesh Yoganathan",
    "Victoria-Sophie Osburg",
    "Andrea Fronzetti Colladon",
    "Vincent Charles",
    "Waldemar Toporowski"
  ],
  "authors_full": [
    {
      "affiliation": [
        "Aston Business School, Aston University, Birmingham, UK"
      ],
      "name": "Vignesh Yoganathan",
      "orcid": "https://orcid.org/0000-0002-9285-4702"
    },
    {
      "affiliation": [
        "MBS School of Business (Montpellier Business School), Montpellier, France"
      ],
      "name": "Victoria-Sophie Osburg",
      "orcid": "https://orcid.org/0000-0001-6762-510X"
    },
    {
      "affiliation": [
        "Department of Engineering, University of Perugia, Perugia, Italy"
      ],
      "name": "Andrea Fronzetti Colladon",
      "orcid": "https://orcid.org/0000-0002-5348-9722"
    },
    {
      "affiliation": [
        "Queen’s Business School, Queen’s University Belfast, Belfast, UK"
      ],
      "name": "Vincent Charles",
      "orcid": "https://orcid.org/0000-0001-8943-5681"
    },
    {
      "affiliation": [
        "Georg-August University of Göttingen, Göttingen, Germany"
      ],
      "name": "Waldemar Toporowski",
      "orcid": null
    }
  ],
  "channel_profiles": {
    "ur": {
      "ai_reason": "服务机器人社会态度的系统综述，涉及用户/消费者对AI的态度和接受度",
      "ai_score": 3.0,
      "domain_score": 4.0,
      "tldr": "研究人口层面服务机器人态度的聚合模式，基于89,541名被试的跨国真实世界数据（2012-2024）。识别出四种稳定的态度画像：积极（adore）、消极（abhor）、冷漠（ignore）和矛盾（unsure）。心理需求（人际互动、自主性、关联性）是态度形成的关键因素。",
      "topic_tags": [
        "消费者行为",
        "用户画像",
        "服务机器人",
        "态度研究"
      ]
    }
  },
  "channels": [
    "ur"
  ],
  "cited_by": 10,
  "date": "2024-11-05",
  "doi": "10.1177/10946705241295841",
  "id": "p_0w-T8zzEYx0f6irz",
  "issue": "1",
  "journal": "JSR",
  "pdf_url": null,
  "source_refs": [
    {
      "channel": "ur",
      "legacy_id": 6459,
      "revision": "718100357f2e33cd77c1d33a36f7754aaa98f070"
    }
  ],
  "title": "Societal Attitudes Toward Service Robots: Adore, Abhor, Ignore, or Unsure?",
  "title_zh": "社会对服务机器人的态度：喜爱、厌恶、忽视还是未知？",
  "unified_ingested_at": "2026-07-12T08:03:25.068701Z",
  "url": "https://doi.org/10.1177/10946705241295841",
  "volume": "28",
  "year": 2024
}
