{
  "abstract": "This paper investigates the application of artificial intelligence (AI) in early-stage recruitment interviews in order to reduce inherent bias, specifically sentiment bias. Traditional interviewers are often subject to several biases, including interviewer bias, social desirability effects, and even confirmation bias. In turn, this leads to non-inclusive hiring practices, and a less diverse workforce. This study further analyzes various AI interventions that are present in the marketplace today such as multimodal platforms and interactive candidate assessment tools in order to gauge the current market usage of AI in early-stage recruitment. However, this paper aims to use a unique AI system that was developed to transcribe and analyze interview dynamics, which emphasize skill and knowledge over emotional sentiments. Results indicate that AI effectively minimizes sentiment-driven biases by 41.2%, suggesting its revolutionizing power in companies' recruitment processes for improved equity and efficiency.",
  "ai_type_tags": [
    "多模态",
    "自然语言处理",
    "AI招聘"
  ],
  "arxiv_id": "2501.09890",
  "authors": [
    "Nishka Lal",
    "Omar Benkraouda"
  ],
  "authors_full": [
    {
      "name": "Nishka Lal"
    },
    {
      "name": "Omar Benkraouda"
    }
  ],
  "channel_profiles": {
    "ob": {
      "ai_reason": "AI招聘面试减偏是核心议题，招聘偏见属OB/HR核心研究",
      "ai_score": 5.0,
      "domain_score": 5.0,
      "tldr": "研究构建可转录并分析面试对话的AI系统，突出技能与知识而非情感，以降低招聘中的情绪偏见。实验显示AI将情感驱动偏见削减41.2%，有望提升招聘公平与效率。",
      "topic_tags": [
        "招聘",
        "偏见",
        "公平性",
        "人机协作"
      ]
    }
  },
  "channels": [
    "ob"
  ],
  "cited_by": 0,
  "date": "2025-01-17",
  "doi": null,
  "id": "p_58RrGTOjXzKIFihZ",
  "issue": null,
  "journal": "arXiv:cs.AI",
  "pdf_url": "https://arxiv.org/pdf/2501.09890v1",
  "source_refs": [
    {
      "channel": "ob",
      "legacy_id": 8582,
      "revision": "bcdda0ebbb6060c402faed2b43fe8ba11a4215bc"
    }
  ],
  "title": "Exploring the Implementation of AI in Early Onset Interviews to Help Mitigate Bias",
  "title_zh": "探索AI在早期诊断访谈中的应用以减少偏倚",
  "unified_ingested_at": "2026-07-12T08:03:25.068701Z",
  "url": "https://arxiv.org/abs/2501.09890v1",
  "volume": null,
  "year": 2025
}
