{
  "abstract": "PRACTICE-ORIENTED ABSTRACT\n                  In September of 2017, Equifax disclosed a data breach that exposed the personal information of 147 million people, including names, Social Security numbers, and addresses. Such high-profile data breaches have rendered traditional forms of identity verification—especially knowledge-based authentication (KBA)—worse than useless: fraudsters have a 92% success rate in KBA screenings, compared to just 46% for genuine customers. In the face of these challenges, digital platforms are turning to sparse alternative data sources and overt verification technologies, often to the detriment of the user experience.\n                  The objective of this research is to design and build a novel approach to identity verification for new platform users using digital behavior data—features that describe how users type and interact during account setup. The system (1) evaluates identity fraud risk for all first-time users, and (2) minimizes the impact on the new user experience by seamlessly analyzing behavior during a platform’s existing onboarding experience. We evaluated and improved the design in four experiments, culminating in an identity fraud detection tool that effectively detects identity fraud for first-time users and supports seamless user experiences.",
  "ai_type_tags": [
    "机器学习",
    "算法决策",
    "人机交互"
  ],
  "arxiv_id": "2023.0088",
  "authors": [
    "David Kim",
    "Joseph S. Valacich",
    "Jeffrey L. Jenkins",
    "David W. Wilson",
    "M. N. V. Ravi Kumar"
  ],
  "authors_full": [
    {
      "affiliation": [
        "Texas Christian University"
      ],
      "name": "David Kim",
      "orcid": null,
      "position": "first"
    },
    {
      "affiliation": [
        "University of Arizona"
      ],
      "name": "Joseph S. Valacich",
      "orcid": "https://orcid.org/0000-0002-3209-3307",
      "position": "middle"
    },
    {
      "affiliation": [
        "Brigham Young University"
      ],
      "name": "Jeffrey L. Jenkins",
      "orcid": "https://orcid.org/0000-0001-8550-4897",
      "position": "middle"
    },
    {
      "affiliation": [
        "Brigham Young University"
      ],
      "name": "David W. Wilson",
      "orcid": null,
      "position": "middle"
    },
    {
      "affiliation": [
        "Northeastern University"
      ],
      "name": "M. N. V. Ravi Kumar",
      "orcid": null,
      "position": "middle"
    },
    {
      "affiliation": [
        "University of Arizona"
      ],
      "name": "Paul Weisgarber",
      "orcid": null,
      "position": "last"
    }
  ],
  "channel_profiles": {
    "ob": {
      "ai_reason": "击键动态身份验证，机器学习/AI核心方法",
      "ai_score": 4.0,
      "domain_score": 5.0,
      "tldr": "针对新用户在平台注册阶段身份欺诈风险高的问题，利用键盘打字行为特征构建身份验证模型，在注册过程中无感知采集数据，实验四轮迭代后实现高准确率检测，同时保持流畅用户体验。",
      "topic_tags": [
        "身份欺诈",
        "行为认证",
        "机器学习",
        "用户体验"
      ]
    }
  },
  "channels": [
    "ob"
  ],
  "cited_by": 0,
  "date": "2026-03-04",
  "doi": "10.1287/isre.2023.0088",
  "id": "p_61YV9cvdvMRGajGe",
  "issue": null,
  "journal": "ISR",
  "pdf_url": null,
  "source_refs": [
    {
      "channel": "ob",
      "legacy_id": 5044,
      "revision": "e5590c77130831830a19cbeab3a44ed6da78f746"
    }
  ],
  "title": "Are You, You? Seamlessly Fighting Identity Fraud with Keystroke Dynamics",
  "title_zh": "你是你吗？利用击键动态无缝打击身份欺诈",
  "unified_ingested_at": "2026-07-12T08:03:25.068701Z",
  "url": "https://doi.org/10.1287/isre.2023.0088",
  "volume": null,
  "year": 2026
}
