{
  "abstract": "Artificial intelligence (AI) recently had its 'iPhone moment' and adoption has drastically accelerated. Quantum computing appears poised to follow suit over the next years. However, while there has been discourse about how to use AI responsibly, there is still little appreciation and awareness among executives, managers, and practitioners about the broader ethical questions and implications raised by the intersection of these emerging technologies. In this article, it is highlighted why quantum computing and AI ethics must be taken seriously by businesspersons and how these technologies affect strategic decisions; moreover, recommendations and action areas are formulated.",
  "ai_type_tags": [
    "AI治理"
  ],
  "arxiv_id": "2312.10081",
  "authors": [
    "Christian Hugo Hoffmann",
    "Frederik F. Flöther"
  ],
  "authors_full": [
    {
      "name": "Christian Hugo Hoffmann"
    },
    {
      "name": "Frederik F. Flöther"
    }
  ],
  "channel_profiles": {
    "ob": {
      "ai_reason": "企业AI伦理决策相关，跨商业伦理与科技",
      "ai_score": 5.0,
      "domain_score": 3.0,
      "tldr": "AI和量子计算正快速商业化，但企业高管和从业者对伦理问题认识不足。文章强调技术伦理在采纳和战略决策中的关键作用，提出行动建议以确保负责任使用。",
      "topic_tags": [
        "伦理",
        "战略",
        "组织变革"
      ]
    }
  },
  "channels": [
    "ob"
  ],
  "cited_by": 0,
  "date": "2023-12-11",
  "doi": "10.1017/qut.2024.5",
  "id": "p_77PhqNbLUoCdwVE8",
  "issue": null,
  "journal": "arXiv:physics.soc-ph",
  "pdf_url": "https://arxiv.org/pdf/2312.10081v2",
  "source_refs": [
    {
      "channel": "ob",
      "legacy_id": 10689,
      "revision": "60844d477886185733c757ab01481e3a2fb4efd7"
    }
  ],
  "title": "Why business adoption of quantum and AI technology must be ethical",
  "title_zh": "量子与人工智能技术的商业采纳必须合乎伦理",
  "unified_ingested_at": "2026-07-12T08:03:25.068701Z",
  "url": "https://arxiv.org/abs/2312.10081v2",
  "volume": null,
  "year": 2023
}
