{
  "abstract": "Empowered by advances in artificial intelligence (AI) and data technologies, service personnel can deliver highly personalized communication using automatically acquired consumer data. However, as firms increasingly rely on such data to enhance service efficiency, consumers’ privacy concerns have become more salient. Drawing on the persuasion knowledge model, this research integrates field data with four controlled experiments to examine how response speed following data acquisition influences consumer reactions. We find that faster (vs. slower) responses, defined as those delivered moderately earlier (vs. later) than consumers’ normative expectations in comparable service contexts, attenuate consumers’ positive reactions to marketing communications. This effect is driven by a serial mediation involving perceived firm eagerness to use information and privacy concerns, highlighting privacy concerns as one of the key psychological mechanisms shaping consumer reactions. Importantly, this negative effect is attenuated when firms provide prewarning messages about upcoming data-based communication, when service involvement is low, or in service recovery contexts. These findings suggest that response speed should be managed strategically. While overly fast responses may backfire in high-involvement or routine services, combining fast responses with prewarning strategies can help firms balance efficiency and privacy perceptions in digital service environments.",
  "ai_type_tags": [
    "AI",
    "AI 客服",
    "AI 推荐"
  ],
  "arxiv_id": null,
  "authors": [
    "Linxiang Lv",
    "Tao He",
    "H Wang",
    "Lingpiao Wang"
  ],
  "authors_full": [
    {
      "affiliation": [
        "Northeastern University"
      ],
      "name": "Linxiang Lv",
      "orcid": "https://orcid.org/0009-0003-5406-0498",
      "position": "first"
    },
    {
      "affiliation": [
        "Virginia Tech"
      ],
      "name": "Tao He",
      "orcid": null,
      "position": "middle"
    },
    {
      "affiliation": [
        "Northeastern University"
      ],
      "name": "H Wang",
      "orcid": null,
      "position": "middle"
    },
    {
      "affiliation": [
        "Changsha University of Science and Technology"
      ],
      "name": "Lingpiao Wang",
      "orcid": "https://orcid.org/0009-0000-2835-9689",
      "position": "last"
    }
  ],
  "channel_profiles": {
    "ur": {
      "ai_reason": "研究AI个性化通信引发的消费者隐私顾虑，4个实验",
      "ai_score": 4.0,
      "domain_score": 5.0,
      "tldr": "结合田野数据与四项实验，检验数据采集后响应速度对消费者反应的影响，发现适度提前（过快）响应会提升感知企业急切度与隐私顾虑，从而削弱正向情绪，且预警信息、低介入或服务恢复情境可缓解该负面效应。",
      "topic_tags": [
        "消费者行为",
        "AI 采用",
        "AI 治理",
        "营销"
      ]
    }
  },
  "channels": [
    "ur"
  ],
  "cited_by": 0,
  "date": "2026-06-12",
  "doi": "10.1177/10946705261447627",
  "id": "p__0TYw5KxzVwJnXXB",
  "issue": null,
  "journal": "JSR",
  "pdf_url": null,
  "source_refs": [
    {
      "channel": "ur",
      "legacy_id": 6371,
      "revision": "77287647fc87ef042919f9b90b1e01ef28e0c63b"
    }
  ],
  "title": "Haste Makes Waste: How Faster Responses after Data Collection Trigger Consumer Privacy Concerns and Reduce Positive Reactions",
  "title_zh": "欲速则不达：数据收集后更快响应如何引发消费者隐私顾虑并降低积极反应",
  "unified_ingested_at": "2026-07-12T08:03:25.068701Z",
  "url": "https://doi.org/10.1177/10946705261447627",
  "volume": null,
  "year": 2026
}
