{
  "abstract": "Effective customer acquisition is crucial for digital platforms, with sequential targeting ensuring that marketing messages are both timely and relevant. The proposed deep recurrent Q-network with attention (DRQN-attention) model enhances this process by optimizing long-term rewards and increasing decision-making transparency. Tested with a data set from a digital bank, the DRQN-attention model has proven to enhance clarity in decision making and outperform traditional methods in boosting long-term rewards. Its attention mechanism acts as a strategic tool for forward planning, pinpointing crucial ad marketing channels that are likely to engage and convert prospects. This capability enables marketers to understand the dynamic targeting strategies of the proposed model that align with customer profiles, dynamic behaviors, and the seasonality of the markets, thereby boosting confidence and effectiveness in their customer acquisition strategies.",
  "ai_type_tags": [
    "机器学习",
    "算法决策",
    "可解释 AI"
  ],
  "arxiv_id": "2022.0529",
  "authors": [
    "Yicheng Song",
    "Wenbo Wang",
    "Song Yao"
  ],
  "authors_full": [
    {
      "affiliation": [
        "University of Minnesota"
      ],
      "name": "Yicheng Song",
      "orcid": "https://orcid.org/0000-0002-9107-814X",
      "position": "first"
    },
    {
      "affiliation": [
        "Hong Kong University of Science and Technology",
        "University of Hong Kong"
      ],
      "name": "Wenbo Wang",
      "orcid": "https://orcid.org/0000-0002-4288-0929",
      "position": "middle"
    },
    {
      "affiliation": [
        "Washington University in St. Louis"
      ],
      "name": "Song Yao",
      "orcid": "https://orcid.org/0000-0002-0339-9649",
      "position": "last"
    }
  ],
  "channel_profiles": {
    "ob": {
      "ai_reason": "深度强化学习用于客户获取，AI为核心议题",
      "ai_score": 5.0,
      "domain_score": 4.0,
      "tldr": "构建带注意力机制的深度递归Q网络（DRQN‑attention）用于数字银行客户获取。该模型通过注意力突出关键营销渠道，提升长期收益和决策透明度，优于传统方法。",
      "topic_tags": [
        "广告",
        "决策",
        "消费者行为"
      ]
    }
  },
  "channels": [
    "ob"
  ],
  "cited_by": 6,
  "date": "2025-03",
  "doi": "10.1287/isre.2022.0529",
  "id": "p_bv7L8N4xS6knmklz",
  "issue": "1",
  "journal": "ISR",
  "pdf_url": null,
  "source_refs": [
    {
      "channel": "ob",
      "legacy_id": 5273,
      "revision": "c4195d3cf669c2b147462c8c69c124a8274b684f"
    }
  ],
  "title": "Customer Acquisition via Explainable Deep Reinforcement Learning",
  "title_zh": "基于可解释深度强化学习的客户获取",
  "unified_ingested_at": "2026-07-12T08:03:25.068701Z",
  "url": "https://doi.org/10.1287/isre.2022.0529",
  "volume": "36",
  "year": 2025
}
