{
  "abstract": "Background Digital therapeutics (DTx) have the potential to improve the accessibility and personalization of cognitive behavioral therapy (CBT) for panic disorder. However, trials comparing DTx with structured active comparators remain limited. Objective We evaluated the efficacy and safety of PanicDoc , a mobile app-based DTx for panic disorder, versus structured psychoeducation. Methods In this open-label randomized trial, 52 patients with panic disorder were randomly assigned to PanicDoc or psychoeducation, both delivered with therapist guidance (n = 26 per group). PanicDoc provided CBT-based modules with algorithm-based personalization over an 8- to 12-week treatment period, whereas the control group received biweekly structured psychoeducation over 12 weeks. The primary outcome was change from baseline in clinician-rated panic severity, assessed using the Panic Disorder Severity Scale (PDSS). Results The PanicDoc group showed significantly greater improvement in PDSS in the end-of-intervention mixed-effects model for repeated measures (least squares mean difference = −3.71, P = .02). Post-treatment Clinical Global Impression–Improvement also favored PanicDoc over controls (t(39)= − 2.78, P = .008). Among participants allocated to PanicDoc , 21 of 26 (80.8%) completed the program; mean app usage was 47.9 (±39.8) minutes/week. No significant between-group differences were observed on self-reported outcomes, although both groups showed within-group improvements on several secondary measures over time. No serious adverse events were reported. Conclusions Guided DTx for panic disorder was associated with greater improvement in clinician-rated panic severity than an active psychoeducation control. However, superiority was not observed on self-reported outcomes, and the open-label design with unblinded clinician ratings warrants cautious interpretation. Trial Registration: KCT0009912 ( https://cris.nih.go.kr/ ).",
  "ai_type_tags": [
    "recommender_personalization"
  ],
  "arxiv_id": null,
  "authors": [
    "Deung Hyun Kang",
    "Hyunchan Hwang",
    "Da Seul Kim",
    "김혜리",
    "Sujin Kwak",
    "Changyu Kim",
    "Soo‐Hee Choi"
  ],
  "authors_full": [
    {
      "name": "Deung Hyun Kang"
    },
    {
      "name": "Hyunchan Hwang"
    },
    {
      "name": "Da Seul Kim"
    },
    {
      "name": "김혜리"
    },
    {
      "name": "Sujin Kwak"
    },
    {
      "name": "Changyu Kim"
    },
    {
      "name": "Soo‐Hee Choi"
    }
  ],
  "channel_profiles": {
    "mh": {
      "ai_reason": "移动端数字疗法App PanicDoc用于恐慌障碍治疗，含算法个性化功能，属数字干预核心应用。随机对照试验验证疗效与安全性。",
      "ai_score": 4,
      "clinical_validation": "prospective",
      "domain_score": 5,
      "evidence_stage": "randomized_controlled_trial",
      "ground_truth_quality": "clinician_assessed",
      "real_world_deployment": false,
      "safety_evaluated": true,
      "tldr": "52例恐慌障碍患者RCT显示，PanicDoc数字疗法在临床评估的恐慌严重程度方面优于结构化心理教育，但自评结果未见显著差异。",
      "topic_tags": [
        "anxiety",
        "digital_intervention",
        "clinical_patients"
      ]
    }
  },
  "channels": [
    "mh"
  ],
  "cited_by": 0,
  "date": "2026-07-09",
  "doi": "10.1016/j.invent.2026.100977",
  "id": "p_e0k-G2XYDPKIFREY",
  "issue": null,
  "journal": "Internet Interventions",
  "pdf_url": "https://www.sciencedirect.com/science/article/pii/S221478292600076X/pdf",
  "source_refs": [
    {
      "channel": "mh",
      "legacy_id": "W7167812957"
    }
  ],
  "title": "Efficacy and safety of a mobile app–based, flexible-schedule digital therapeutic intervention versus psychoeducation for panic disorder: An open-label randomized controlled trial",
  "title_zh": "移动端灵活方案数字疗法对比心理教育治疗恐慌障碍的疗效与安全性：一项开放标签随机对照试验",
  "unified_ingested_at": "2026-07-21T05:24:36.613649Z",
  "url": "https://doi.org/10.1016/j.invent.2026.100977",
  "volume": null,
  "year": 2026
}
