{
  "abstract": null,
  "ai_type_tags": [
    "自动语音识别",
    "自动评分",
    "机器学习"
  ],
  "arxiv_id": null,
  "authors": [],
  "authors_full": null,
  "channel_profiles": {
    "ob": {
      "ai_reason": "自动化语音识别偏见属AI招聘核心议题",
      "ai_score": 5.0,
      "domain_score": 5.0,
      "tldr": "研究利用自动语音识别（ASR）对求职面试进行自动评分，考察其在不同人口特征（性别、口音等）上的评分差异。结果显示ASR系统对特定群体产生系统性偏差，导致评分偏低，提示需进行公平性审计与改进。",
      "topic_tags": [
        "招聘",
        "偏见",
        "算法决策",
        "人机交互"
      ]
    }
  },
  "channels": [
    "ob"
  ],
  "cited_by": 0,
  "date": "2024-10-31",
  "doi": "10.1037/apl0001247.supp",
  "id": "p_F1U56_cljFfKDKVK",
  "issue": null,
  "journal": "JAP",
  "pdf_url": null,
  "source_refs": [
    {
      "channel": "ob",
      "legacy_id": 1014,
      "revision": "e5590c77130831830a19cbeab3a44ed6da78f746"
    }
  ],
  "title": "Supplemental Material for Automated Speech Recognition Bias in Personnel Selection: The Case of Automatically Scored Job Interviews",
  "title_zh": "人员选拔中自动语音识别偏见的补充材料：自动评分求职面试案例",
  "unified_ingested_at": "2026-07-12T08:03:25.068701Z",
  "url": "https://doi.org/10.1037/apl0001247.supp",
  "volume": null,
  "year": 2024
}
