{
  "abstract": "We study the data-integrated, price-setting newsvendor problem in which the price–demand relationship is described by some parametric model with unknown parameters. We develop the operational data analytics (ODA) formulation of this problem that features a data-integration model and a validation model. The data-integration model consists of a class of functions called the operational statistics. Each operational statistic maps the available data to the ordering decision. The validation model finds, among the set of candidate operational statistics, the ordering decision that leads to the highest actual profit, which is unknown because of the unknown demand parameters. This ODA framework leads to a consistent estimate of the profit function with which we optimize the pricing decision. The derived quantity and price decisions demonstrate robust profit performance even when the sample size is very small in relation to the demand variability. Compared with the conventional approach with which the unknown parameters are estimated and then the decisions are optimized, the ODA framework produces significantly superior performance in the mean, standard deviation, and minimum of the profit, suggesting the robustness of the ODA solution especially in the small-sample regime.  This paper was accepted by David Simchi-Levi, operations management.  Supplemental Material: The online appendix and data files are available at https://doi.org/10.1287/mnsc.2021.02227 .",
  "ai_type_tags": [
    "Operational Data Analytics",
    "Parametric Modeling",
    "Machine Learning",
    "Optimization"
  ],
  "arxiv_id": "2021.02227",
  "authors": [
    "Leon Yang Chu",
    "Qi Feng",
    "J. George Shanthikumar",
    "Zuo‐Jun Max Shen",
    "Jian Wu"
  ],
  "authors_full": [
    {
      "affiliation": [
        "Cheung Kong Graduate School of Business"
      ],
      "name": "Leon Yang Chu",
      "orcid": "https://orcid.org/0000-0003-1512-114X",
      "position": "first"
    },
    {
      "affiliation": [
        "Purdue University West Lafayette"
      ],
      "name": "Qi Feng",
      "orcid": "https://orcid.org/0000-0001-6176-044X",
      "position": "middle"
    },
    {
      "affiliation": [
        "Purdue University West Lafayette"
      ],
      "name": "J. George Shanthikumar",
      "orcid": "https://orcid.org/0000-0002-7345-4674",
      "position": "middle"
    },
    {
      "affiliation": [
        "University of Hong Kong"
      ],
      "name": "Zuo‐Jun Max Shen",
      "orcid": "https://orcid.org/0000-0003-4538-8312",
      "position": "middle"
    },
    {
      "affiliation": [
        "Purdue University West Lafayette"
      ],
      "name": "Jian Wu",
      "orcid": "https://orcid.org/0000-0002-8629-8009",
      "position": "last"
    }
  ],
  "channel_profiles": {
    "ob": {
      "ai_reason": "数据驱动运营分析用于定价决策，参数模型与数据集成方法",
      "ai_score": 3.0,
      "domain_score": 5.0,
      "tldr": "针对价格设定的新报童问题，采用操作数据解析（ODA）框架，通过操作统计量直接映射数据到订货决策并利用验证模型选优，实现小样本下稳健的利润表现，显著优于先估计再优化的传统方法。",
      "topic_tags": [
        "决策",
        "运营管理",
        "需求预测"
      ]
    }
  },
  "channels": [
    "ob"
  ],
  "cited_by": 7,
  "date": "2025-08",
  "doi": "10.1287/mnsc.2021.02227",
  "id": "p_kXBmlBoPg__mLian",
  "issue": "8",
  "journal": "MgmtSci",
  "pdf_url": null,
  "source_refs": [
    {
      "channel": "ob",
      "legacy_id": 3852,
      "revision": "4cab5c9d294e13105a04ad21db72b25b85ff13f7"
    }
  ],
  "title": "Solving the Price-Setting Newsvendor Problem with Parametric Operational Data Analytics (ODA)",
  "title_zh": "基于参数化运营数据分析的定价报童问题求解",
  "unified_ingested_at": "2026-07-12T08:03:25.068701Z",
  "url": "https://doi.org/10.1287/mnsc.2021.02227",
  "volume": "71",
  "year": 2025
}
