{
  "abstract": null,
  "ai_type_tags": [
    "智能体/Agent",
    "多模态",
    "GenAI"
  ],
  "arxiv_id": null,
  "authors": [
    "Xuejun Du",
    "Pengcheng An",
    "Justin Leung",
    "April Li",
    "Linda E. Chapman"
  ],
  "authors_full": [
    {
      "affiliation": [],
      "name": "Xuejun Du",
      "orcid": "https://orcid.org/0000-0003-2358-0434"
    },
    {
      "affiliation": [],
      "name": "Pengcheng An",
      "orcid": "https://orcid.org/0000-0002-7705-2031"
    },
    {
      "affiliation": [],
      "name": "Justin Leung",
      "orcid": "https://orcid.org/0000-0001-5363-6609"
    },
    {
      "affiliation": [],
      "name": "April Li",
      "orcid": null
    },
    {
      "affiliation": [],
      "name": "Linda E. Chapman",
      "orcid": null
    },
    {
      "affiliation": [],
      "name": "Jian Zhao",
      "orcid": null
    }
  ],
  "channel_profiles": {
    "ur": {
      "ai_reason": "设计并探究人类-AI在数字艺术疗法中的共同创造，HCI设计研究+人-AI协作",
      "ai_score": 5.0,
      "domain_score": 5.0,
      "tldr": "DeepThInk 项目研究人机协同创作在数字艺术治疗中的设计与评估。通过构建原型并进行用户实验，揭示协作模式对情感表达和疗效感知的促进作用，提出交互设计原则，为心理干预提供新途径。",
      "topic_tags": [
        "人机协作",
        "服务设计",
        "用户体验(UX)"
      ]
    }
  },
  "channels": [
    "ur"
  ],
  "cited_by": 76,
  "date": "2024-01",
  "doi": "10.1016/j.ijhcs.2023.103139",
  "id": "p_lvzsAbLjQFbyaGub",
  "issue": null,
  "journal": "IJHCS",
  "pdf_url": null,
  "source_refs": [
    {
      "channel": "ur",
      "legacy_id": 976,
      "revision": "e8f86c1a9ce1a0b8c92bbeff71c5e2d4775ae062"
    }
  ],
  "title": "DeepThInk: Designing and probing human-AI co-creation in digital art therapy",
  "title_zh": "DeepThInk：数字艺术治疗中人机协作创作的设计与探索",
  "unified_ingested_at": "2026-07-12T08:03:25.068701Z",
  "url": "https://doi.org/10.1016/j.ijhcs.2023.103139",
  "volume": "181",
  "year": 2024
}
