{
  "abstract": "Humble AI (Knowles et al., 2023) argues for cautiousness in AI development and deployments through scepticism (accounting for limitations of statistical learning), curiosity (accounting for unexpected outcomes), and commitment (accounting for multifaceted values beyond performance). We present a real-world case study for humble AI in the domain of algorithmic hiring. Specifically, we evaluate virtual screening algorithms in a widely used hiring platform that matches candidates to job openings. There are several challenges in misrecognition and stereotyping in such contexts that are difficult to assess through standard fairness and trust frameworks; e.g., someone with a non-traditional background is less likely to rank highly. We demonstrate technical feasibility of how humble AI principles can be translated to practice through uncertainty quantification of ranks, entropy estimates, and a user experience that highlights algorithmic unknowns. We describe preliminary discussions with focus groups made up of recruiters. Future user studies seek to evaluate whether the higher cognitive load of a humble AI system fosters a climate of trust in its outcomes.",
  "ai_type_tags": [
    "算法决策",
    "可解释AI",
    "机器学习"
  ],
  "arxiv_id": "2505.20918",
  "authors": [
    "Rahul Nair",
    "Inge Vejsbjerg",
    "Elizabeth Daly",
    "Christos Varytimidis",
    "Bran Knowles"
  ],
  "authors_full": [
    {
      "name": "Rahul Nair"
    },
    {
      "name": "Inge Vejsbjerg"
    },
    {
      "name": "Elizabeth Daly"
    },
    {
      "name": "Christos Varytimidis"
    },
    {
      "name": "Bran Knowles"
    }
  ],
  "channel_profiles": {
    "ob": {
      "ai_reason": "直接研究算法招聘公平性，强相关HR管理议题",
      "ai_score": 5.0,
      "domain_score": 4.0,
      "tldr": "招聘平台虚拟筛选算法面临误识别与刻板化挑战，难以通过传统公平信任框架评估非传统背景候选人排序偏低等问题。研究通过不确定性量化和熵估计技术，将谦逊AI的谨慎、好奇与坚守原则转化为实践，设计突出算法未知因素的用户界面。初步焦点小组讨论表明，高认知负载或能促进结果信任，后续用户研究将进一步验证。",
      "topic_tags": [
        "招聘",
        "算法管理",
        "信任",
        "人机协作"
      ]
    }
  },
  "channels": [
    "ob"
  ],
  "cited_by": 0,
  "date": "2025-05-27",
  "doi": null,
  "id": "p_LxLLwajOOAxUZ-Lu",
  "issue": null,
  "journal": "arXiv:cs.LG",
  "pdf_url": "https://arxiv.org/pdf/2505.20918v1",
  "source_refs": [
    {
      "channel": "ob",
      "legacy_id": 8488,
      "revision": "60844d477886185733c757ab01481e3a2fb4efd7"
    }
  ],
  "title": "Humble AI in the real-world: the case of algorithmic hiring",
  "title_zh": "现实世界中的谦逊 AI：算法招聘案例研究",
  "unified_ingested_at": "2026-07-12T08:03:25.068701Z",
  "url": "https://arxiv.org/abs/2505.20918v1",
  "volume": null,
  "year": 2025
}
