{
  "abstract": null,
  "ai_type_tags": [
    "对话式AI",
    "语音生成",
    "文本生成",
    "多模态"
  ],
  "arxiv_id": null,
  "authors": [
    "Hilde Voorveld",
    "Andreas Panteli",
    "Yoni Schirris",
    "Carolin Ischen",
    "Evangelos Kanoulas"
  ],
  "authors_full": [
    {
      "affiliation": [
        "University of Amsterdam"
      ],
      "name": "Hilde Voorveld",
      "orcid": null
    },
    {
      "affiliation": [
        "Netherlands Cancer Institute (NKI)"
      ],
      "name": "Andreas Panteli",
      "orcid": null
    },
    {
      "affiliation": [
        "Netherlands Cancer Institute (NKI)"
      ],
      "name": "Yoni Schirris",
      "orcid": null
    },
    {
      "affiliation": [
        "University of Amsterdam"
      ],
      "name": "Carolin Ischen",
      "orcid": null
    },
    {
      "affiliation": [
        "Informatics Institute University of"
      ],
      "name": "Evangelos Kanoulas",
      "orcid": null
    },
    {
      "affiliation": [
        "Tilburg University"
      ],
      "name": "Tom Lentz",
      "orcid": null
    }
  ],
  "channel_profiles": {
    "ur": {
      "ai_reason": "评估用户对语音/文本agent的感知，人机交互用户实验",
      "ai_score": 4.0,
      "domain_score": 4.0,
      "tldr": "对比文字和语音代理的劝说效果，探讨韵律与信息结构匹配对拟人化、感知个性化及品牌态度的影响。实验采用2×2因子设计，测量用户主观评分。结果发现，语音代理配合信息结构的韵律显著提升拟人化和品牌好感度，文本代理的个性化感知较低。",
      "topic_tags": [
        "劝说式交互",
        "语音代理",
        "文本代理",
        "品牌态度"
      ]
    }
  },
  "channels": [
    "ur"
  ],
  "cited_by": 8,
  "date": "2024-11-14",
  "doi": "10.1080/0144929x.2024.2420871",
  "id": "p_rIq3P8R3z2NAjXuP",
  "issue": "12",
  "journal": "BIT",
  "pdf_url": null,
  "source_refs": [
    {
      "channel": "ur",
      "legacy_id": 1710,
      "revision": "d7931e8c2bd20d81cc4f90c1a45935b98302fa03"
    }
  ],
  "title": "Examining the persuasiveness of text and voice agents: prosody aligned with information structure increases human-likeness, perceived personalisation and brand attitude",
  "title_zh": "文本与语音代理说服力研究：韵律配合信息结构提升类人性、感知个性化及品牌态度",
  "unified_ingested_at": "2026-07-12T08:03:25.068701Z",
  "url": "https://doi.org/10.1080/0144929x.2024.2420871",
  "volume": "44",
  "year": 2024
}
