{
  "abstract": "Humans and robots are increasingly working in personal and professional settings. In workplace settings, humans and robots may work together as colleagues, potentially leading to social expectations, or violation thereof. Extant research has primarily sought to understand social interactions and expectations in personal rather than professional settings, and none of these studies have examined negative outcomes arising from violations of social expectations. This paper reports the results of a 2x3 online experiment that used a unique first-person perspective video to immerse participants in a collaborative workplace setting. The results are nuanced and reveal that while robots are expected to act in accordance with social expectations despite human behavior, there are benefits for robots perceived as being the bigger person in the face of human rudeness. Theoretical and practical implications are provided which discuss the import of these findings for the design of social robots.",
  "ai_type_tags": [
    "机器人",
    "人机交互",
    "多模态"
  ],
  "arxiv_id": "2503.16932",
  "authors": [
    "Kate Letheren",
    "Nicole Robinson"
  ],
  "authors_full": [
    {
      "name": "Kate Letheren"
    },
    {
      "name": "Nicole Robinson"
    }
  ],
  "channel_profiles": {
    "ob": {
      "ai_reason": "工作场所人机互动研究，职场心理行为核心议题",
      "ai_score": 4.0,
      "domain_score": 5.0,
      "tldr": "研究通过2x3在线实验，使用第一人称视角视频让参与者沉浸于协作工作场景，考察人类对机器人报复意图的感知及社会期望违背的后果。结果表明，尽管机器人被预期无论人类行为如何都应遵守社会规范，但在面对人类不礼貌行为时，被视为\"更大度\"的机器人反而能获得积极评价。研究为职场社交机器人的设计提供了理论与实践启示。",
      "topic_tags": [
        "人机协作",
        "工作设计",
        "信任",
        "算法管理"
      ]
    }
  },
  "channels": [
    "ob"
  ],
  "cited_by": 0,
  "date": "2025-03-21",
  "doi": null,
  "id": "p_zNJCxexRF2maQKaV",
  "issue": null,
  "journal": "arXiv:cs.RO",
  "pdf_url": "https://arxiv.org/pdf/2503.16932v1",
  "source_refs": [
    {
      "channel": "ob",
      "legacy_id": 8538,
      "revision": "69a3687b8e24c7a1fd2a6a659d3d5778cea66a3d"
    }
  ],
  "title": "Rude Humans and Vengeful Robots: Examining Human Perceptions of Robot Retaliatory Intentions in Professional Settings",
  "title_zh": "粗鲁的人类与复仇的机器人：考察职场中人类对机器人报复意图的感知",
  "unified_ingested_at": "2026-07-12T08:03:25.068701Z",
  "url": "https://arxiv.org/abs/2503.16932v1",
  "volume": null,
  "year": 2025
}
